xmrzapp/__init__.py
xmrzapp/reader.py
xmrzapp/segmentation.py
xmrzapp/utils.py
xmrzapp/weights/face_detector/deploy.prototxt
xmrzapp/weights/face_detector/res10_300x300_ssd_iter_140000.caffemodel
xmrzapp/weights/mrz_detector/mrz_seg.tflite
xmrzapp-25.10.9.dist-info/METADATA
xmrzapp-25.10.9.dist-info/WHEEL
xmrzapp-25.10.9.dist-info/top_level.txt
xmrzapp-25.10.9.dist-info/RECORD
