Metadata-Version: 2.4
Name: xmrzapp
Version: 25.10.9
Summary: Extended MRZ Passport Reader From Image
Home-page: https://github.com/devnbugs/xmrzapp
Author: rhsalisu
Project-URL: Bug Tracker, https://github.com/devnbugs/xmrzapp/issues
Classifier: Programming Language :: Python :: 3
Classifier: Programming Language :: Python :: 3.10
Classifier: License :: OSI Approved :: MIT License
Classifier: Operating System :: OS Independent
Requires-Python: >=3.8
Requires-Dist: opencv_python_headless>=4.5.3.56
Requires-Dist: scipy>=1.5.2
Requires-Dist: imutils>=0.5.4
Requires-Dist: deskew>=0.10.36
Requires-Dist: easyocr>=1.7.1
Requires-Dist: tensorflow>=2.9.0
Provides-Extra: cpu
Requires-Dist: tensorflow-cpu>=2.9.0; extra == "cpu"
Provides-Extra: gpu
Requires-Dist: tensorflow>=2.9.0; extra == "gpu"
Dynamic: author
Dynamic: classifier
Dynamic: description
Dynamic: description-content-type
Dynamic: home-page
Dynamic: project-url
Dynamic: provides-extra
Dynamic: requires-dist
Dynamic: requires-python
Dynamic: summary
